cson.py
setup.py
python_cson.egg-info/PKG-INFO
python_cson.egg-info/SOURCES.txt
python_cson.egg-info/dependency_links.txt
python_cson.egg-info/entry_points.txt
python_cson.egg-info/not-zip-safe
python_cson.egg-info/top_level.txt