Metadata-Version: 1.1
Name: python-cson
Version: 1.0.9
Summary: Python library for CSON (schema-compressed JSON)
Home-page: https://github.com/lifthrasiir/cson
Author: Russell Leake
Author-email: gt3389b@gmail.com
License: MIT
Download-URL: https://github.com/gt3389b/python-cson/
Keywords: json cson cursive
Platform: UNKNOWN
